awsa/__init__.py
awsa/awsa.py
awsa-0.1.4.dist-info/METADATA
awsa-0.1.4.dist-info/WHEEL
awsa-0.1.4.dist-info/top_level.txt
awsa-0.1.4.dist-info/RECORD
