Metadata-Version: 2.1
Name: awsa
Version: 0.1.4
Summary: AISAK-O agent for information collection and summary.
Author: Mandela Logan
Author-email: mandelakorilogan@gmail.com
Classifier: Programming Language :: Python :: 3
Classifier: License :: OSI Approved :: MIT License
Classifier: Operating System :: OS Independent
Requires-Python: >=3.6
Requires-Dist: torch
Requires-Dist: transformers
Requires-Dist: beautifulsoup4
Requires-Dist: edge-tts
Requires-Dist: nest-asyncio
Requires-Dist: IPython
